[
  {
    "line": 1,
    "elements": [
      {
        "start_timestamp": "2022-08-16T10:12:37.351Z",
        "before": [
          {
            "result": {
              "duration": 23363000000,
              "status": "passed"
            },
            "match": {
              "location": "Steps.Hooks.start()"
            }
          }
        ],
        "line": 13,
        "name": "customer service",
        "description": "",
        "id": "search;customer-service",
        "after": [
          {
            "result": {
              "duration": 940000000,
              "status": "passed"
            },
            "match": {
              "location": "Steps.Hooks.end()"
            }
          }
        ],
        "type": "scenario",
        "keyword": "Scenario",
        "steps": [
          {
            "result": {
              "duration": 11366000000,
              "status": "passed"
            },
            "line": 14,
            "name": "user select a subject heading",
            "match": {
              "location": "Steps.HomeStep.user_select_a_subject_heading()"
            },
            "keyword": "* "
          },
          {
            "result": {
              "duration": 4576000000,
              "status": "passed"
            },
            "line": 15,
            "name": "user then enter email address and order reference",
            "match": {
              "location": "Steps.HomeStep.user_then_enter_email_address_and_order_reference()"
            },
            "keyword": "* "
          },
          {
            "result": {
              "duration": 70000000,
              "status": "passed"
            },
            "line": 16,
            "name": "user then attach file",
            "match": {
              "location": "Steps.HomeStep.user_then_attach_file()"
            },
            "keyword": "* "
          },
          {
            "result": {
              "duration": 256000000,
              "status": "passed"
            },
            "line": 17,
            "name": "user enter message",
            "match": {
              "location": "Steps.HomeStep.user_enter_message()"
            },
            "keyword": "* "
          },
          {
            "result": {
              "duration": 12520000000,
              "status": "passed"
            },
            "line": 18,
            "name": "user cliks send",
            "match": {
              "location": "Steps.HomeStep.user_cliks_send()"
            },
            "keyword": "* "
          }
        ],
        "tags": [
          {
            "name": "@regression"
          },
          {
            "name": "@f"
          }
        ]
      }
    ],
    "name": "search",
    "description": "",
    "id": "search",
    "keyword": "Feature",
    "uri": "file:src/test/resources/Features/home.feature",
    "tags": []
  }
]